__init__.py
src/__init__.py
src/app.py
src/constants.py
src/score.py
src/score_types.py
src/validation.py
scoreapi-0.0.1.dist-info/METADATA
scoreapi-0.0.1.dist-info/WHEEL
scoreapi-0.0.1.dist-info/licenses/LICENSE
scoreapi-0.0.1.dist-info/RECORD
