Metadata-Version: 2.1
Name: scoreapi
Version: 0.0.1
Summary: Payment Score API
Project-URL: Homepage, https://github.com/openfinanceafrica/scoreapi
Project-URL: Bug Tracker, https://github.com/openfinanceafrica/scoreapi/issues
Author-email: Example Author <author@example.com>
License-File: LICENSE
Classifier: License :: OSI Approved :: MIT License
Classifier: Operating System :: OS Independent
Classifier: Programming Language :: Python :: 3
Requires-Python: >=3.7
